<!--
 =================================================================
  Licensed Materials - Property of IBM

  WebSphere Commerce

  (C) Copyright IBM Corp. 2015 All Rights Reserved.

  US Government Users Restricted Rights - Use, duplication or
  disclosure restricted by GSA ADP Schedule Contract with
  IBM Corp.
 =================================================================
-->

<PortConfiguration>
	<Table tableName="ORDADJTXEX">
		<ForeignKey parentTableName="ORDADJUST">
			<Member columnName="ORDADJUST_ID" referencedColumnName="ORDADJUST_ID"/>
		</ForeignKey>
		<ForeignKey parentTableName="TAXCGRY">
			<Member columnName="TAXCGRY_ID" referencedColumnName="TAXCGRY_ID"/>
		</ForeignKey>
	</Table>
</PortConfiguration>